{"_type":"export","__export_format":4,"__export_date":"2023-07-13T19:26:59.141Z","__export_source":"insomnia.desktop.app:v2023.2.2","resources":[{"_id":"req_693f60e0abc54d58bdf6ad036f2e65e6","parentId":"fld_1347ffac6d1b4eb6bfcbc8e2c2cffd1e","modified":1689193321688,"created":1689191632156,"url":"localhost:3001/boletos","name":"boletos","description":"","method":"GET","body":{},"parameters":[],"headers":[],"authentication":{},"metaSortKey":-1689191632156,"isPrivate":false,"settingStoreCookies":true,"settingSendCookies":true,"settingDisableRenderRequestBody":false,"settingEncodeUrl":true,"settingRebuildPath":true,"settingFollowRedirects":"global","_type":"request"},{"_id":"fld_1347ffac6d1b4eb6bfcbc8e2c2cffd1e","parentId":"wrk_f06ef17aa47a4daa8dd72047d7258fc6","modified":1689125681423,"created":1689125658832,"name":"GreenAcesso","description":"","environment":{},"environmentPropertyOrder":null,"metaSortKey":-1689125658832,"_type":"request_group"},{"_id":"wrk_f06ef17aa47a4daa8dd72047d7258fc6","parentId":null,"modified":1689276381338,"created":1684507434252,"name":"Projects","description":"","scope":"collection","_type":"workspace"},{"_id":"req_1005513456024a5a88e9a81edbd154db","parentId":"fld_1347ffac6d1b4eb6bfcbc8e2c2cffd1e","modified":1689193558729,"created":1689193549274,"url":"localhost:3001/boletos?relatorio=1","name":"boletos base64","description":"","method":"GET","body":{},"parameters":[],"headers":[],"authentication":{},"metaSortKey":-1689158658604.5,"isPrivate":false,"settingStoreCookies":true,"settingSendCookies":true,"settingDisableRenderRequestBody":false,"settingEncodeUrl":true,"settingRebuildPath":true,"settingFollowRedirects":"global","_type":"request"},{"_id":"req_630fca3c234b4236a8a2fe1e5902e77c","parentId":"fld_1347ffac6d1b4eb6bfcbc8e2c2cffd1e","modified":1689194411912,"created":1689194406227,"url":"localhost:3001/boletos?nome=JOSE&valor_inicial=100&valor_final=200&id_lote=2","name":"boletos filtros","description":"","method":"GET","body":{},"parameters":[],"headers":[],"authentication":{},"metaSortKey":-1689142171828.75,"isPrivate":false,"settingStoreCookies":true,"settingSendCookies":true,"settingDisableRenderRequestBody":false,"settingEncodeUrl":true,"settingRebuildPath":true,"settingFollowRedirects":"global","_type":"request"},{"_id":"req_8580422b85ba459cbff7aa76ac74cd9d","parentId":"fld_1347ffac6d1b4eb6bfcbc8e2c2cffd1e","modified":1689276107180,"created":1689125685053,"url":"localhost:3001/import","name":"import csv","description":"","method":"POST","body":{"mimeType":"multipart/form-data","params":[{"id":"pair_3291b0f527e04cc792ae2b003df3f8a1","name":"file","value":"","description":"","type":"file","fileName":"/Users/robertopimenta/Documents/greenacesso/arquivos/import_boletos_sindico.csv"}]},"parameters":[],"headers":[{"name":"Content-Type","value":"multipart/form-data"}],"authentication":{},"metaSortKey":-1689125685053,"isPrivate":false,"settingStoreCookies":true,"settingSendCookies":true,"settingDisableRenderRequestBody":false,"settingEncodeUrl":true,"settingRebuildPath":true,"settingFollowRedirects":"global","_type":"request"},{"_id":"req_11146f78cd534006bdf3d1bfeb6b8d39","parentId":"fld_1347ffac6d1b4eb6bfcbc8e2c2cffd1e","modified":1689192126398,"created":1689192116808,"url":"localhost:3001/import-pdf","name":"import pdf","description":"","method":"POST","body":{"mimeType":"multipart/form-data","params":[{"id":"pair_3291b0f527e04cc792ae2b003df3f8a1","name":"file","value":"","description":"","type":"file","fileName":"/Users/robertopimenta/Documents/repositorios/greenacesso/arquivos/fake_pdf.pdf"}]},"parameters":[],"headers":[{"name":"Content-Type","value":"multipart/form-data"}],"authentication":{},"metaSortKey":-1687427272016,"isPrivate":false,"settingStoreCookies":true,"settingSendCookies":true,"settingDisableRenderRequestBody":false,"settingEncodeUrl":true,"settingRebuildPath":true,"settingFollowRedirects":"global","_type":"request"},{"_id":"env_e7fc7b9c4157248e68f664e72b3b78ac239e54cb","parentId":"wrk_f06ef17aa47a4daa8dd72047d7258fc6","modified":1684507434343,"created":1684507434343,"name":"Base Environment","data":{},"dataPropertyOrder":null,"color":null,"isPrivate":false,"metaSortKey":1684507434343,"_type":"environment"},{"_id":"jar_e7fc7b9c4157248e68f664e72b3b78ac239e54cb","parentId":"wrk_f06ef17aa47a4daa8dd72047d7258fc6","modified":1684507434418,"created":1684507434418,"name":"Default Jar","cookies":[],"_type":"cookie_jar"},{"_id":"spc_35df80bad96b4d968ec5fac67d987cb5","parentId":"wrk_f06ef17aa47a4daa8dd72047d7258fc6","modified":1684507434253,"created":1684507434253,"fileName":"Trybecar","contents":"","contentType":"yaml","_type":"api_spec"}]}